Metadata-Version: 2.1
Name: Mensajes-Capdetrons
Version: 7.0
Summary: Un paquete para saludar y despedir
Home-page: https://www.julio.dev
Author: Julio Capdevila Perea
Author-email: jcapdevilaperea@telefonica.net
Classifier: Environment :: Console
Classifier: Intended Audience :: Developers
Classifier: License :: OSI Approved :: MIT License
Classifier: Operating System :: Microsoft :: Windows :: Windows 10
Classifier: Programming Language :: Python
Classifier: Programming Language :: Python :: 3.11
Classifier: Topic :: Utilities
License-File: LICENSE
Requires-Dist: numpy (>=1.23.0)
